mjms/__init__.py
mjms-1.2.1.dist-info/METADATA
mjms-1.2.1.dist-info/WHEEL
mjms-1.2.1.dist-info/top_level.txt
mjms-1.2.1.dist-info/RECORD
