Metadata-Version: 2.1
Name: mjms
Version: 1.2.1
Summary: Python client for mailsrv.marcusj.org
Home-page: https://github.com/AgeOfMarcus/mjms
Author: AgeOfMarcus
Author-email: marcus@marcusweinberger.com
Requires-Dist: requests
